multi_mcp/__init__.py
multi_mcp/__main__.py
multi_mcp/cli.py
multi_mcp/constants.py
multi_mcp/py.typed
multi_mcp/server.py
multi_mcp/settings.py
multi_mcp/config/__init__.py
multi_mcp/config/config.override.example.yaml
multi_mcp/config/config.yaml
multi_mcp/memory/__init__.py
multi_mcp/memory/store.py
multi_mcp/models/__init__.py
multi_mcp/models/cli_executor.py
multi_mcp/models/config.py
multi_mcp/models/litellm_client.py
multi_mcp/models/resolver.py
multi_mcp/prompts/__init__.py
multi_mcp/prompts/chat.md
multi_mcp/prompts/codereview-consolidation.md
multi_mcp/prompts/codereview.md
multi_mcp/prompts/compare.md
multi_mcp/prompts/debate-step1.md
multi_mcp/prompts/debate-step2.md
multi_mcp/schemas/__init__.py
multi_mcp/schemas/base.py
multi_mcp/schemas/chat.py
multi_mcp/schemas/codereview.py
multi_mcp/schemas/compare.py
multi_mcp/schemas/debate.py
multi_mcp/tools/__init__.py
multi_mcp/tools/chat.py
multi_mcp/tools/codereview.py
multi_mcp/tools/compare.py
multi_mcp/tools/debate.py
multi_mcp/tools/models.py
multi_mcp/utils/__init__.py
multi_mcp/utils/artifacts.py
multi_mcp/utils/consolidation.py
multi_mcp/utils/context.py
multi_mcp/utils/files.py
multi_mcp/utils/helpers.py
multi_mcp/utils/json_parser.py
multi_mcp/utils/llm_runner.py
multi_mcp/utils/log_helpers.py
multi_mcp/utils/mcp_decorator.py
multi_mcp/utils/mcp_factory.py
multi_mcp/utils/mcp_logger.py
multi_mcp/utils/message_builder.py
multi_mcp/utils/paths.py
multi_mcp/utils/prompts.py
multi_mcp/utils/repository.py
multi_mcp/utils/request_logger.py
multi_mcp-0.1.1.dist-info/licenses/LICENSE
multi_mcp-0.1.1.dist-info/METADATA
multi_mcp-0.1.1.dist-info/WHEEL
multi_mcp-0.1.1.dist-info/entry_points.txt
multi_mcp-0.1.1.dist-info/top_level.txt
multi_mcp-0.1.1.dist-info/RECORD
