Metadata-Version: 2.4
Name: multi-mcp
Version: 0.1.1
Summary: Multi-Model Code Review and Analysis MCP Server for Claude Code
Author-email: Multi-MCP Team <multi.mcp.team@gmail.com>
License-Expression: MIT
Project-URL: Homepage, https://github.com/religa/multi_mcp
Project-URL: Repository, https://github.com/religa/multi_mcp
Project-URL: Issues, https://github.com/religa/multi_mcp/issues
Keywords: agents,ai,ai-agents,ai-agents-cli,ai-code-review,anthropic,claude,claude-commands,claude-mcp,claude-skills,code-analysis,developer-tools,gemini,gpt,llm,llm-orchestration,mcp,mcp-agent,model-context-protocol,multi-agent,multi-model,openai
Classifier: Development Status :: 4 - Beta
Classifier: Intended Audience :: Developers
Classifier: Operating System :: OS Independent
Classifier: Programming Language :: Python :: 3
Classifier: Programming Language :: Python :: 3.11
Classifier: Programming Language :: Python :: 3.12
Classifier: Programming Language :: Python :: 3.13
Classifier: Topic :: Software Development :: Quality Assurance
Classifier: Topic :: Software Development :: Testing
Classifier: Typing :: Typed
Requires-Python: >=3.11
License-File: LICENSE
Requires-Dist: fastmcp>=2.13
Requires-Dist: litellm>=1.80.8
Requires-Dist: pydantic>=2.12.0
Requires-Dist: pydantic-settings>=2.12.0
Requires-Dist: python-dotenv>=1.0.0
Requires-Dist: pyyaml>=6.0
Provides-Extra: dev
Requires-Dist: pytest>=9.0.0; extra == "dev"
Requires-Dist: twine>=6.0.0; extra == "dev"
Requires-Dist: pytest-asyncio>=0.23.0; extra == "dev"
Requires-Dist: pytest-mock>=3.15.0; extra == "dev"
Requires-Dist: pytest-cov>=4.1.0; extra == "dev"
Requires-Dist: pytest-timeout>=2.2.0; extra == "dev"
Requires-Dist: pytest-xdist>=3.5.0; extra == "dev"
Requires-Dist: pytest-recording>=0.13.4; extra == "dev"
Requires-Dist: vcrpy>=7.0.0; extra == "dev"
Requires-Dist: httpx>=0.26.0; extra == "dev"
Requires-Dist: ruff>=0.14.0; extra == "dev"
Requires-Dist: pyright>=1.1.407; extra == "dev"
Dynamic: license-file
